<?xml version="1.0" encoding="UTF-8"?>
<!DOCTYPE mapper PUBLIC "-//mybatis.org//DTD Mapper 3.0//EN" "https://mybatis.org/dtd/mybatis-3-mapper.dtd">
<mapper namespace="com.example.dzcom.infrastructure.persistence.mapper.account.UserCredentialMapper">
    <select id="selectById" resultType="com.example.dzcom.infrastructure.persistence.entity.account.UserCredentialEntity">
        select * from aiw_user_credential where biz_id = #{bizId}
    </select>
    <select id="selectPasswordByUserBizId" resultType="com.example.dzcom.infrastructure.persistence.entity.account.UserCredentialEntity">
        select * from aiw_user_credential
        where user_biz_id = #{userBizId} and credential_type = 'PASSWORD' and is_deleted = 0
    </select>
    <insert id="save">
        insert into aiw_user_credential
        (biz_id, user_biz_id, credential_type, secret_hash, hash_algorithm, credential_version,
         changed_at, failed_attempts, locked_until, created_at, updated_at, is_deleted)
        values
        (#{bizId}, #{userBizId}, #{credentialType}, #{secretHash}, #{hashAlgorithm}, #{credentialVersion},
         #{changedAt}, #{failedAttempts}, #{lockedUntil}, #{createdAt}, #{updatedAt}, #{deleted})
        on duplicate key update
        secret_hash = values(secret_hash), hash_algorithm = values(hash_algorithm),
        credential_version = values(credential_version), changed_at = values(changed_at),
        failed_attempts = values(failed_attempts), locked_until = values(locked_until),
        updated_at = values(updated_at), is_deleted = values(is_deleted)
    </insert>
    <update id="softDeleteByUserBizId">
        update aiw_user_credential set is_deleted = 1 where user_biz_id = #{userBizId}
    </update>
</mapper>
